rtl/seven_seg_decoder.v
// =====================================================================
// Module      : seven_seg_decoder
// Description : Converts a single 4-bit BCD digit (0-9) into the
//               7-bit pattern needed to light up segments a-g on a
//               common-cathode seven-segment display (Basys3 style).
//
// Segment map : seg = {g, f, e, d, c, b, a}   (bit 6 = g ... bit 0 = a)
// Polarity    : Basys3 seven-seg is ACTIVE-LOW, so a '0' turns a
//               segment ON. We define the patterns here in
//               active-low form to match the board directly.
// =====================================================================

module seven_seg_decoder (
    input  wire [3:0] digit,    // 0-9 BCD digit
    output reg  [6:0] seg       // active-low segment pattern {g,f,e,d,c,b,a}
);

    always @(*) begin
        case (digit)
            4'd0: seg = 7'b1000000; // 0
            4'd1: seg = 7'b1111001; // 1
            4'd2: seg = 7'b0100100; // 2
            4'd3: seg = 7'b0110000; // 3
            4'd4: seg = 7'b0011001; // 4
            4'd5: seg = 7'b0010010; // 5
            4'd6: seg = 7'b0000010; // 6
            4'd7: seg = 7'b1111000; // 7
            4'd8: seg = 7'b0000000; // 8
            4'd9: seg = 7'b0010000; // 9
            default: seg = 7'b1111111; // blank / off
        endcase
    end

endmodule

rtl/display_mux.v
// =====================================================================
// Module      : display_mux
// Description : The Basys3 board has 4 seven-segment digits that
//               SHARE the same 7 segment lines. Only one digit can be
//               lit at a time, so we rapidly scan through all 4
//               digits (fast enough that the human eye sees them as
//               simultaneously lit - this is called time-division
//               multiplexing / persistence of vision).
//
//               Digit layout on display: [MM tens][MM units][SS tens][SS units]
//               (Minutes:Seconds shown by default - see top module)
//
// Concept     : Multiplexing is a core VLSI/digital design technique
//               used to drive many outputs with few physical pins.
// =====================================================================

module display_mux (
    input  wire       clk,
    input  wire        rst,
    input  wire [3:0] digit0,   // rightmost digit  (seconds units)
    input  wire [3:0] digit1,   // seconds tens
    input  wire [3:0] digit2,   // minutes units
    input  wire [3:0] digit3,   // leftmost digit   (minutes tens)
    output reg  [3:0] anode,    // active-low: selects which digit is powered
    output wire [3:0] bcd_out   // currently selected digit's BCD value
);

    // Refresh counter: scans through digits fast enough to avoid flicker.
    // 100 MHz / 2^16 ~= 1.5 kHz per-digit refresh - well above flicker threshold.
    reg [15:0] refresh_counter;
    wire [1:0] digit_select;

    always @(posedge clk) begin
        if (rst)
            refresh_counter <= 16'd0;
        else
            refresh_counter <= refresh_counter + 1'b1;
    end

    assign digit_select = refresh_counter[15:14]; // top 2 bits cycle 0,1,2,3

    // Select which digit's BCD value is currently being displayed
    reg [3:0] bcd_sel;
    always @(*) begin
        case (digit_select)
            2'b00: bcd_sel = digit0;
            2'b01: bcd_sel = digit1;
            2'b10: bcd_sel = digit2;
            2'b11: bcd_sel = digit3;
        endcase
    end
    assign bcd_out = bcd_sel;

    // Active-low anode select: only one digit powered at a time
    always @(*) begin
        case (digit_select)
            2'b00: anode = 4'b1110; // enable digit0 (rightmost)
            2'b01: anode = 4'b1101; // enable digit1
            2'b10: anode = 4'b1011; // enable digit2
            2'b11: anode = 4'b0111; // enable digit3 (leftmost)
        endcase
    end

endmodule

rtl/bin_to_bcd.v
// =====================================================================
// Module      : bin_to_bcd
// Description : Converts a binary value (0-59 max) into two BCD
//               digits: tens and units. Needed because the seven-
//               segment display shows decimal digits, not binary.
//
// Example     : minutes = 45 (binary 101101)
//               -> tens = 4, units = 5
//
// Note        : Since our max input is 59, a simple combinational
//               divide/modulo by 10 is small enough to synthesize
//               efficiently (no need for a full shift-add-3 BCD
//               algorithm here).
// =====================================================================

module bin_to_bcd (
    input  wire [5:0] bin_value,   // 0-59
    output wire [3:0] tens,        // 0-5
    output wire [3:0] units        // 0-9
);

    assign tens  = bin_value / 10;
    assign units = bin_value % 10;

endmodule

rtl/alarm_comparator.v
// =====================================================================
// Module      : alarm_comparator
// Description : Compares the LIVE current time (hours:minutes) against
//               a user-programmed alarm time (alarm_hour:alarm_minute).
//               When they match AND alarm_enable is asserted AND
//               seconds == 0 (so the alarm fires once per matching
//               minute, not 60 times), alarm_out goes high.
//
// Concept     : This is a pure combinational/registered comparator -
//               the same building block used in RTC ICs, microwave
//               timers, and industrial timer relays.
//
// Design note : We gate on seconds == 0 so the alarm pulses for one
//               full second at the start of the matching minute,
//               instead of staying high for the entire 60-second
//               window (which would be a less realistic alarm clock
//               behavior).
// =====================================================================

module alarm_comparator (
    input  wire        clk,
    input  wire        rst,
    input  wire [4:0]  hours,         // current hour   (0-23)
    input  wire [5:0]  minutes,       // current minute (0-59)
    input  wire [5:0]  seconds,       // current second (0-59)
    input  wire [4:0]  alarm_hour,    // alarm hour set by user   (0-23)
    input  wire [5:0]  alarm_minute,  // alarm minute set by user (0-59)
    input  wire         alarm_enable,  // 1 = alarm armed, 0 = alarm disabled
    output reg          alarm_out      // 1 = alarm is currently ringing
);

    wire time_match;

    // Combinational match check: does current HH:MM equal alarm HH:MM?
    assign time_match = (hours   == alarm_hour)   &&
                         (minutes == alarm_minute) &&
                         (seconds  == 6'd0);

    always @(posedge clk) begin
        if (rst) begin
            alarm_out <= 1'b0;
        end else if (alarm_enable && time_match) begin
            alarm_out <= 1'b1;
        end else begin
            alarm_out <= 1'b0;
        end
    end

endmodule

rtl/hours_counter.v
// =====================================================================
// Module      : hours_counter
// Description : Counts hours from 0 to 23 (24-hour format). Increments
//               once every time minutes_counter rolls over (every 60
//               minutes). Rolls over from 23 back to 0 at midnight.
// =====================================================================

module hours_counter (
    input  wire       clk,
    input  wire        rst,
    input  wire        tick_in,   // = minutes_counter.rollover
    output reg  [4:0] hours       // 0 - 23 (5 bits enough: max 23)
);

    always @(posedge clk) begin
        if (rst) begin
            hours <= 5'd0;
        end else if (tick_in) begin
            if (hours == 5'd23) begin
                hours <= 5'd0;     // midnight rollover
            end else begin
                hours <= hours + 1'b1;
            end
        end
    end

endmodule

rtl/minutes_counter.v
// =====================================================================
// Module      : minutes_counter
// Description : Counts minutes from 0 to 59. Increments once every
//               time the seconds_counter rolls over (i.e., every 60
//               seconds). On reaching 59 and getting another tick,
//               it rolls over to 0 and pulses 'rollover' which drives
//               the hours_counter.
// =====================================================================

module minutes_counter (
    input  wire       clk,
    input  wire        rst,
    input  wire        tick_in,    // = seconds_counter.rollover
    output reg  [5:0] minutes,    // 0 - 59
    output reg         rollover    // pulses high for 1 cycle when 59 -> 0
);

    always @(posedge clk) begin
        if (rst) begin
            minutes  <= 6'd0;
            rollover <= 1'b0;
        end else if (tick_in) begin
            if (minutes == 6'd59) begin
                minutes  <= 6'd0;
                rollover <= 1'b1;   // tell hours_counter to increment
            end else begin
                minutes  <= minutes + 1'b1;
                rollover <= 1'b0;
            end
        end else begin
            rollover <= 1'b0;
        end
    end

endmodule

rtl/seconds_counter.v
// =====================================================================
// Module      : seconds_counter
// Description : Counts seconds from 0 to 59. On reaching 59 and
//               receiving the next tick, it rolls over to 0 and
//               asserts 'rollover' for exactly one cycle, which the
//               minutes counter uses as its own "tick" input.
//
// Concept     : This is a modulo-60 (mod-60) BCD-friendly counter.
//               It demonstrates the classic VLSI counter design
//               pattern used in every real-time clock IC.
// =====================================================================

module seconds_counter (
    input  wire       clk,
    input  wire        rst,
    input  wire        tick_1hz,   // 1 Hz enable pulse from clock_divider
    output reg  [5:0] seconds,    // 0 - 59 (6 bits enough: max 59)
    output reg         rollover    // pulses high for 1 cycle when 59 -> 0
);

    always @(posedge clk) begin
        if (rst) begin
            seconds  <= 6'd0;
            rollover <= 1'b0;
        end else if (tick_1hz) begin
            if (seconds == 6'd59) begin
                seconds  <= 6'd0;
                rollover <= 1'b1;   // tell minutes_counter to increment
            end else begin
                seconds  <= seconds + 1'b1;
                rollover <= 1'b0;
            end
        end else begin
            rollover <= 1'b0;       // rollover is a single-cycle pulse
        end
    end

endmodule

rtl/clock_divider.v
// =====================================================================
// Module      : clock_divider
// Description : Divides the 100 MHz Basys3 system clock down to a
//               precise 1 Hz "tick" pulse that drives the seconds
//               counter. One tick = exactly one real-world second.
//
// Concept     : FPGA boards only give you a fast system clock
//               (100 MHz on Basys3). A digital clock needs to count
//               in real seconds, so we need a clock divider that
//               counts 100,000,000 fast-clock edges and then pulses
//               once. That pulse is what the rest of the design uses
//               as its "1-second heartbeat".
//
// Author      : Seshuu (VLSI Course Project)
// =====================================================================

module clock_divider #(
    // DIVISOR = number of clk edges per output tick.
    // Default = 100,000,000 for real hardware (100 MHz -> 1 Hz).
    // For SIMULATION ONLY, instantiate with a small override, e.g.
    // clock_divider #(.DIVISOR(10)) so the testbench doesn't have to
    // wait 100 million real clock edges to see one "second" tick.
    // The RTL logic exercised is identical either way - only the
    // count value changes.
    parameter integer DIVISOR = 100_000_000
) (
    input  wire clk,        // 100 MHz board clock (Basys3 system clock)
    input  wire rst,        // synchronous active-high reset
    output reg  tick_1hz    // goes high for exactly 1 clk cycle every 1 second
);

    // 27 bits is enough to count up to 100,000,000 (2^27 = 134,217,728)
    reg [26:0] count_reg;

    always @(posedge clk) begin
        if (rst) begin
            count_reg <= 27'd0;
            tick_1hz  <= 1'b0;
        end else begin
            if (count_reg == DIVISOR - 1) begin
                count_reg <= 27'd0;
                tick_1hz  <= 1'b1;   // pulse high for one clk cycle
            end else begin
                count_reg <= count_reg + 1'b1;
                tick_1hz  <= 1'b0;
            end
        end
    end

endmodule

rtl/digital_clock_alarm_top.v
// =====================================================================
// Module      : digital_clock_alarm_top
// Description : Top-level module for the VLSI-Based Digital Clock
//               with Alarm Functionality. Connects all submodules:
//
//                 clk (100 MHz)
//                   |
//                   v
//               clock_divider --tick_1hz--> seconds_counter
//                                                |
//                                          rollover (every 60s)
//                                                v
//                                          minutes_counter
//                                                |
//                                          rollover (every 60m)
//                                                v
//                                          hours_counter
//                                                |
//                          hours, minutes, seconds ---+
//                                                       v
//                                              alarm_comparator --> alarm_out
//                                                       |
//                                          bin_to_bcd (x2) --> seven_seg
//                                                       |
//                                              display_mux --> seg, anode
//
// Board       : Xilinx Artix-7 (Basys3)
// Display     : Shows MM:SS by default (minutes:seconds) on the 4
//               available seven-segment digits. Hours are exposed as
//               a top-level output (hours_out) for simulation /
//               waveform verification and can be wired to extra LEDs.
// =====================================================================

module digital_clock_alarm_top #(
    // Pass-through parameter: override for fast simulation, e.g.
    // digital_clock_alarm_top #(.CLK_DIVISOR(10)) u_dut (...)
    // Default = 100,000,000 for real 100 MHz Basys3 hardware.
    parameter integer CLK_DIVISOR = 100_000_000
) (
    input  wire        clk,            // 100 MHz Basys3 system clock
    input  wire        rst,            // active-high reset (BTN center)
    input  wire        alarm_enable,   // switch SW0: arm/disarm alarm
    input  wire [4:0]  alarm_hour_in,  // switches: alarm hour setting   (0-23)
    input  wire [5:0]  alarm_min_in,   // switches: alarm minute setting (0-59)

    output wire [6:0]  seg,            // seven-seg segment lines (active-low)
    output wire [3:0]  anode,          // seven-seg digit select (active-low)
    output wire        alarm_led,      // LED that lights when alarm rings
    output wire [4:0]  hours_out,      // current hour   (for sim/debug/LEDs)
    output wire [5:0]  minutes_out,    // current minute (for sim/debug)
    output wire [5:0]  seconds_out     // current second (for sim/debug)
);

    // -----------------------------------------------------------------
    // Internal wires connecting the time-keeping chain
    // -----------------------------------------------------------------
    wire        tick_1hz;
    wire        sec_rollover;
    wire        min_rollover;
    wire [5:0]  seconds;
    wire [5:0]  minutes;
    wire [4:0]  hours;
    wire        alarm_out;

    assign hours_out   = hours;
    assign minutes_out = minutes;
    assign seconds_out = seconds;
    assign alarm_led   = alarm_out;

    // -----------------------------------------------------------------
    // 1. Clock divider: 100 MHz -> 1 Hz tick
    // -----------------------------------------------------------------
    clock_divider #(
        .DIVISOR (CLK_DIVISOR)
    ) u_clock_divider (
        .clk      (clk),
        .rst      (rst),
        .tick_1hz (tick_1hz)
    );

    // -----------------------------------------------------------------
    // 2. Seconds counter (0-59)
    // -----------------------------------------------------------------
    seconds_counter u_seconds_counter (
        .clk      (clk),
        .rst      (rst),
        .tick_1hz (tick_1hz),
        .seconds  (seconds),
        .rollover (sec_rollover)
    );

    // -----------------------------------------------------------------
    // 3. Minutes counter (0-59), driven by seconds rollover
    // -----------------------------------------------------------------
    minutes_counter u_minutes_counter (
        .clk      (clk),
        .rst      (rst),
        .tick_in  (sec_rollover),
        .minutes  (minutes),
        .rollover (min_rollover)
    );

    // -----------------------------------------------------------------
    // 4. Hours counter (0-23), driven by minutes rollover
    // -----------------------------------------------------------------
    hours_counter u_hours_counter (
        .clk     (clk),
        .rst     (rst),
        .tick_in (min_rollover),
        .hours   (hours)
    );

    // -----------------------------------------------------------------
    // 5. Alarm comparator
    // -----------------------------------------------------------------
    alarm_comparator u_alarm_comparator (
        .clk          (clk),
        .rst          (rst),
        .hours        (hours),
        .minutes      (minutes),
        .seconds      (seconds),
        .alarm_hour   (alarm_hour_in),
        .alarm_minute (alarm_min_in),
        .alarm_enable (alarm_enable),
        .alarm_out    (alarm_out)
    );

    // -----------------------------------------------------------------
    // 6. BCD conversion for display (showing MM:SS on 4 digits)
    // -----------------------------------------------------------------
    wire [3:0] sec_tens, sec_units, min_tens, min_units;

    bin_to_bcd u_bcd_seconds (
        .bin_value (seconds),
        .tens      (sec_tens),
        .units     (sec_units)
    );

    bin_to_bcd u_bcd_minutes (
        .bin_value (minutes),
        .tens      (min_tens),
        .units     (min_units)
    );

    // -----------------------------------------------------------------
    // 7. Display multiplexer + seven-segment decoder
    // -----------------------------------------------------------------
    wire [3:0] bcd_selected;

    display_mux u_display_mux (
        .clk     (clk),
        .rst     (rst),
        .digit0  (sec_units),   // rightmost  = seconds units
        .digit1  (sec_tens),    // seconds tens
        .digit2  (min_units),   // minutes units
        .digit3  (min_tens),    // leftmost   = minutes tens
        .anode   (anode),
        .bcd_out (bcd_selected)
    );

    seven_seg_decoder u_seven_seg_decoder (
        .digit (bcd_selected),
        .seg   (seg)
    );

endmodule

tb/tb_waveform_demo.v
// =====================================================================
// Module      : tb_waveform_demo
// Description : A SHORT, focused testbench used only to generate a
//               small, clean .vcd waveform file for documentation /
//               GitHub screenshots. The full correctness testbench is
//               tb_digital_clock_alarm_top.v (run that one for
//               pass/fail verification). This file exists purely so
//               the waveform image isn't a 25+ MB file nobody can
//               open quickly in GTKWave.
//
// What it shows:
//   1. Reset
//   2. Seconds counting 0 -> a few ticks
//   3. Seconds rollover (59 -> 0) causing minutes to increment
//   4. An alarm match event (alarm_led pulsing high)
//
// Run with:
//   iverilog -o demo_out tb/tb_waveform_demo.v rtl/*.v
//   vvp demo_out
//   gtkwave waveforms/demo_waveform.vcd
// =====================================================================

`timescale 1ns/1ps

module tb_waveform_demo;

    reg        clk;
    reg        rst;
    reg        alarm_enable;
    reg [4:0]  alarm_hour_in;
    reg [5:0]  alarm_min_in;

    wire [6:0] seg;
    wire [3:0] anode;
    wire       alarm_led;
    wire [4:0] hours_out;
    wire [5:0] minutes_out;
    wire [5:0] seconds_out;

    // Small divisor so seconds tick by quickly in simulated time
    localparam SIM_DIVISOR = 10;

    digital_clock_alarm_top #(
        .CLK_DIVISOR (SIM_DIVISOR)
    ) dut (
        .clk           (clk),
        .rst           (rst),
        .alarm_enable  (alarm_enable),
        .alarm_hour_in (alarm_hour_in),
        .alarm_min_in  (alarm_min_in),
        .seg           (seg),
        .anode         (anode),
        .alarm_led     (alarm_led),
        .hours_out     (hours_out),
        .minutes_out   (minutes_out),
        .seconds_out   (seconds_out)
    );

    always #5 clk = ~clk;

    task wait_ticks(input integer n);
        integer k;
        begin
            for (k = 0; k < n; k = k + 1) begin
                @(posedge dut.u_clock_divider.tick_1hz);
                @(posedge clk);
                @(posedge clk);
            end
        end
    endtask

    initial begin
        clk           = 0;
        rst           = 1;
        alarm_enable  = 1;
        alarm_hour_in = 5'd0;
        alarm_min_in  = 6'd1;   // alarm set for 00:01:00

        repeat (5) @(posedge clk);
        rst = 0;

        wait_ticks(65); // show seconds counting, the 59->0 rollover into
                         // minute 1, and the alarm firing at 00:01:00

        $display("Demo waveform complete: h=%0d m=%0d s=%0d alarm_led=%b",
                  hours_out, minutes_out, seconds_out, alarm_led);
        $finish;
    end

    // -----------------------------------------------------------------
    // NOTE FOR VIVADO USERS: $dumpfile/$dumpvars below produce a VCD
    // file, which is the Icarus Verilog / GTKWave waveform format.
    // Vivado's XSim does NOT need this — when running this testbench
    // inside Vivado, just open the Waveform window after "Run
    // Behavioral Simulation" and drag hours_out, minutes_out,
    // seconds_out, alarm_led, seg, and anode into it directly. Vivado
    // captures everything natively in its own .wdb database. This
    // dumpfile call is harmless to leave in (Vivado will just ignore
    // or skip it), but it's not how you'll view waveforms there.
    // -----------------------------------------------------------------
    initial begin
        $dumpfile("waveforms/demo_waveform.vcd");
        $dumpvars(1, dut);
    end

endmodule

waveforms/demo_waveform.vcd
$date
	Sat Jun 20 09:17:40 2026
$end
$version
	Icarus Verilog
$end
$timescale
	1ps
$end
$scope module tb_waveform_demo $end
$scope module dut $end
$var wire 1 ! alarm_enable $end
$var wire 5 " alarm_hour_in [4:0] $end
$var wire 1 # alarm_led $end
$var wire 6 $ alarm_min_in [5:0] $end
$var wire 1 % clk $end
$var wire 5 & hours_out [4:0] $end
$var wire 6 ' minutes_out [5:0] $end
$var wire 1 ( rst $end
$var wire 6 ) seconds_out [5:0] $end
$var wire 1 * tick_1hz $end
$var wire 7 + seg [6:0] $end
$var wire 6 , seconds [5:0] $end
$var wire 4 - sec_units [3:0] $end
$var wire 4 . sec_tens [3:0] $end
$var wire 1 / sec_rollover $end
$var wire 6 0 minutes [5:0] $end
$var wire 4 1 min_units [3:0] $end
$var wire 4 2 min_tens [3:0] $end
$var wire 1 3 min_rollover $end
$var wire 5 4 hours [4:0] $end
$var wire 4 5 bcd_selected [3:0] $end
$var wire 4 6 anode [3:0] $end
$var wire 1 7 alarm_out $end
$var parameter 32 8 CLK_DIVISOR $end
$upscope $end
$upscope $end
$enddefinitions $end
$comment Show the parameter values. $end
$dumpall
b1010 8
$end
#0
$dumpvars
x7
bx 6
bx 5
bx 4
x3
bx 2
bx 1
bx 0
x/
bx .
bx -
bx ,
bx +
x*
bx )
1(
bx '
bx &
0%
b1 $
x#
b0 "
1!
$end
#5000
b1000000 +
b1110 6
b0 5
b0 -
b0 .
b0 1
b0 2
0*
0/
b0 )
b0 ,
03
b0 '
b0 0
b0 &
b0 4
0#
07
1%
#10000
0%
#15000
1%
#20000
0%
#25000
1%
#30000
0%
#35000
1%
#40000
0%
#45000
0(
1%
#50000
0%
#55000
1%
#60000
0%
#65000
1%
#70000
0%
#75000
1%
#80000
0%
#85000
1%
#90000
0%
#95000
1%
#100000
0%
#105000
1%
#110000
0%
#115000
1%
#120000
0%
#125000
1%
#130000
0%
#135000
1*
1%
#140000
0%
#145000
b1111001 +
b1 5
b1 -
0*
b1 )
b1 ,
1%
#150000
0%
#155000
1%
#160000
0%
#165000
1%
#170000
0%
#175000
1%
#180000
0%
#185000
1%
#190000
0%
#195000
1%
#200000
0%
#205000
1%
#210000
0%
#215000
1%
#220000
0%
#225000
1%
#230000
0%
#235000
1*
1%
#240000
0%
#245000
b100100 +
b10 5
b10 -
0*
b10 )
b10 ,
1%
#250000
0%
#255000
1%
#260000
0%
#265000
1%
#270000
0%
#275000
1%
#280000
0%
#285000
1%
#290000
0%
#295000
1%
#300000
0%
#305000
1%
#310000
0%
#315000
1%
#320000
0%
#325000
1%
#330000
0%
#335000
1*
1%
#340000
0%
#345000
b110000 +
b11 5
b11 -
0*
b11 )
b11 ,
1%
#350000
0%
#355000
1%
#360000
0%
#365000
1%
#370000
0%
#375000
1%
#380000
0%
#385000
1%
#390000
0%
#395000
1%
#400000
0%
#405000
1%
#410000
0%
#415000
1%
#420000
0%
#425000
1%
#430000
0%
#435000
1*
1%
#440000
0%
#445000
b11001 +
b100 5
b100 -
0*
b100 )
b100 ,
1%
#450000
0%
#455000
1%
#460000
0%
#465000
1%
#470000
0%
#475000
1%
#480000
0%
#485000
1%
#490000
0%
#495000
1%
#500000
0%
#505000
1%
#510000
0%
#515000
1%
#520000
0%
#525000
1%
#530000
0%
#535000
1*
1%
#540000
0%
#545000
b10010 +
b101 5
b101 -
0*
b101 )
b101 ,
1%
#550000
0%
#555000
1%
#560000
0%
#565000
1%
#570000
0%
#575000
1%
#580000
0%
#585000
1%
#590000
0%
#595000
1%
#600000
0%
#605000
1%
#610000
0%
#615000
1%
#620000
0%
#625000
1%
#630000
0%
#635000
1*
1%
#640000
0%
#645000
b10 +
b110 5
b110 -
0*
b110 )
b110 ,
1%
#650000
0%
#655000
1%
#660000
0%
#665000
1%
#670000
0%
#675000
1%
#680000
0%
#685000
1%
#690000
0%
#695000
1%
#700000
0%
#705000
1%
#710000
0%
#715000
1%
#720000
0%
#725000
1%
#730000
0%
#735000
1*
1%
#740000
0%
#745000
b1111000 +
b111 5
b111 -
0*
b111 )
b111 ,
1%
#750000
0%
#755000
1%
#760000
0%
#765000
1%
#770000
0%
#775000
1%
#780000
0%
#785000
1%
#790000
0%
#795000
1%
#800000
0%
#805000
1%
#810000
0%
#815000
1%
#820000
0%
#825000
1%
#830000
0%
#835000
1*
1%
#840000
0%
#845000
b0 +
b1000 5
b1000 -
0*
b1000 )
b1000 ,
1%
#850000
0%
#855000
1%
#860000
0%
#865000
1%
#870000
0%
#875000
1%
#880000
0%
#885000
1%
#890000
0%
#895000
1%
#900000
0%
#905000
1%
#910000
0%
#915000
1%
#920000
0%
#925000
1%
#930000
0%
#935000
1*
1%
#940000
0%
#945000
b10000 +
b1001 5
b1001 -
0*
b1001 )
b1001 ,
1%
#950000
0%
#955000
1%
#960000
0%
#965000
1%
#970000
0%
#975000
1%
#980000
0%
#985000
1%
#990000
0%
#995000
1%
#1000000
0%
#1005000
1%
#1010000
0%
#1015000
1%
#1020000
0%
#1025000
1%
#1030000
0%
#1035000
1*
1%
#1040000
0%
#1045000
b1000000 +
b0 5
b0 -
b1 .
0*
b1010 )
b1010 ,
1%
#1050000
0%
#1055000
1%
#1060000
0%
#1065000
1%
#1070000
0%
#1075000
1%
#1080000
0%
#1085000
1%
#1090000
0%
#1095000
1%
#1100000
0%
#1105000
1%
#1110000
0%
#1115000
1%
#1120000
0%
#1125000
1%
#1130000
0%
#1135000
1*
1%
#1140000
0%
#1145000
b1111001 +
b1 5
b1 -
0*
b1011 )
b1011 ,
1%
#1150000
0%
#1155000
1%
#1160000
0%
#1165000
1%
#1170000
0%
#1175000
1%
#1180000
0%
#1185000
1%
#1190000
0%
#1195000
1%
#1200000
0%
#1205000
1%
#1210000
0%
#1215000
1%
#1220000
0%
#1225000
1%
#1230000
0%
#1235000
1*
1%
#1240000
0%
#1245000
b100100 +
b10 5
b10 -
0*
b1100 )
b1100 ,
1%
#1250000
0%
#1255000
1%
#1260000
0%
#1265000
1%
#1270000
0%
#1275000
1%
#1280000
0%
#1285000
1%
#1290000
0%
#1295000
1%
#1300000
0%
#1305000
1%
#1310000
0%
#1315000
1%
#1320000
0%
#1325000
1%
#1330000
0%
#1335000
1*
1%
#1340000
0%
#1345000
b110000 +
b11 5
b11 -
0*
b1101 )
b1101 ,
1%
#1350000
0%
#1355000
1%
#1360000
0%
#1365000
1%
#1370000
0%
#1375000
1%
#1380000
0%
#1385000
1%
#1390000
0%
#1395000
1%
#1400000
0%
#1405000
1%
#1410000
0%
#1415000
1%
#1420000
0%
#1425000
1%
#1430000
0%
#1435000
1*
1%
#1440000
0%
#1445000
b11001 +
b100 5
b100 -
0*
b1110 )
b1110 ,
1%
#1450000
0%
#1455000
1%
#1460000
0%
#1465000
1%
#1470000
0%
#1475000
1%
#1480000
0%
#1485000
1%
#1490000
0%
#1495000
1%
#1500000
0%
#1505000
1%
#1510000
0%
#1515000
1%
#1520000
0%
#1525000
1%
#1530000
0%
#1535000
1*
1%
#1540000
0%
#1545000
b10010 +
b101 5
b101 -
0*
b1111 )
b1111 ,
1%
#1550000
0%
#1555000
1%
#1560000
0%
#1565000
1%
#1570000
0%
#1575000
1%
#1580000
0%
#1585000
1%
#1590000
0%
#1595000
1%
#1600000
0%
#1605000
1%
#1610000
0%
#1615000
1%
#1620000
0%
#1625000
1%
#1630000
0%
#1635000
1*
1%
#1640000
0%
#1645000
b10 +
b110 5
b110 -
0*
b10000 )
b10000 ,
1%
#1650000
0%
#1655000
1%
#1660000
0%
#1665000
1%
#1670000
0%
#1675000
1%
#1680000
0%
#1685000
1%
#1690000
0%
#1695000
1%
#1700000
0%
#1705000
1%
#1710000
0%
#1715000
1%
#1720000
0%
#1725000
1%
#1730000
0%
#1735000
1*
1%
#1740000
0%
#1745000
b1111000 +
b111 5
b111 -
0*
b10001 )
b10001 ,
1%
#1750000
0%
#1755000
1%
#1760000
0%
#1765000
1%
#1770000
0%
#1775000
1%
#1780000
0%
#1785000
1%
#1790000
0%
#1795000
1%
#1800000
0%
#1805000
1%
#1810000
0%
#1815000
1%
#1820000
0%
#1825000
1%
#1830000
0%
#1835000
1*
1%
#1840000
0%
#1845000
b0 +
b1000 5
b1000 -
0*
b10010 )
b10010 ,
1%
#1850000
0%
#1855000
1%
#1860000
0%
#1865000
1%
#1870000
0%
#1875000
1%
#1880000
0%
#1885000
1%
#1890000
0%
#1895000
1%
#1900000
0%
#1905000
1%
#1910000
0%
#1915000
1%
#1920000
0%
#1925000
1%
#1930000
0%
#1935000
1*
1%
#1940000
0%
#1945000
b10000 +
b1001 5
b1001 -
0*
b10011 )
b10011 ,
1%
#1950000
0%
#1955000
1%
#1960000
0%
#1965000
1%
#1970000
0%
#1975000
1%
#1980000
0%
#1985000
1%
#1990000
0%
#1995000
1%
#2000000
0%
#2005000
1%
#2010000
0%
#2015000
1%
#2020000
0%
#2025000
1%
#2030000
0%
#2035000
1*
1%
#2040000
0%
#2045000
b1000000 +
b0 5
b0 -
b10 .
0*
b10100 )
b10100 ,
1%
#2050000
0%
#2055000
1%
#2060000
0%
#2065000
1%
#2070000
0%
#2075000
1%
#2080000
0%
#2085000
1%
#2090000
0%
#2095000
1%
#2100000
0%
#2105000
1%
#2110000
0%
#2115000
1%
#2120000
0%
#2125000
1%
#2130000
0%
#2135000
1*
1%
#2140000
0%
#2145000
b1111001 +
b1 5
b1 -
0*
b10101 )
b10101 ,
1%
#2150000
0%
#2155000
1%
#2160000
0%
#2165000
1%
#2170000
0%
#2175000
1%
#2180000
0%
#2185000
1%
#2190000
0%
#2195000
1%
#2200000
0%
#2205000
1%
#2210000
0%
#2215000
1%
#2220000
0%
#2225000
1%
#2230000
0%
#2235000
1*
1%
#2240000
0%
#2245000
b100100 +
b10 5
b10 -
0*
b10110 )
b10110 ,
1%
#2250000
0%
#2255000
1%
#2260000
0%
#2265000
1%
#2270000
0%
#2275000
1%
#2280000
0%
#2285000
1%
#2290000
0%
#2295000
1%
#2300000
0%
#2305000
1%
#2310000
0%
#2315000
1%
#2320000
0%
#2325000
1%
#2330000
0%
#2335000
1*
1%
#2340000
0%
#2345000
b110000 +
b11 5
b11 -
0*
b10111 )
b10111 ,
1%
#2350000
0%
#2355000
1%
#2360000
0%
#2365000
1%
#2370000
0%
#2375000
1%
#2380000
0%
#2385000
1%
#2390000
0%
#2395000
1%
#2400000
0%
#2405000
1%
#2410000
0%
#2415000
1%
#2420000
0%
#2425000
1%
#2430000
0%
#2435000
1*
1%
#2440000
0%
#2445000
b11001 +
b100 5
b100 -
0*
b11000 )
b11000 ,
1%
#2450000
0%
#2455000
1%
#2460000
0%
#2465000
1%
#2470000
0%
#2475000
1%
#2480000
0%
#2485000
1%
#2490000
0%
#2495000
1%
#2500000
0%
#2505000
1%
#2510000
0%
#2515000
1%
#2520000
0%
#2525000
1%
#2530000
0%
#2535000
1*
1%
#2540000
0%
#2545000
b10010 +
b101 5
b101 -
0*
b11001 )
b11001 ,
1%
#2550000
0%
#2555000
1%
#2560000
0%
#2565000
1%
#2570000
0%
#2575000
1%
#2580000
0%
#2585000
1%
#2590000
0%
#2595000
1%
#2600000
0%
#2605000
1%
#2610000
0%
#2615000
1%
#2620000
0%
#2625000
1%
#2630000
0%
#2635000
1*
1%
#2640000
0%
#2645000
b10 +
b110 5
b110 -
0*
b11010 )
b11010 ,
1%
#2650000
0%
#2655000
1%
#2660000
0%
#2665000
1%
#2670000
0%
#2675000
1%
#2680000
0%
#2685000
1%
#2690000
0%
#2695000
1%
#2700000
0%
#2705000
1%
#2710000
0%
#2715000
1%
#2720000
0%
#2725000
1%
#2730000
0%
#2735000
1*
1%
#2740000
0%
#2745000
b1111000 +
b111 5
b111 -
0*
b11011 )
b11011 ,
1%
#2750000
0%
#2755000
1%
#2760000
0%
#2765000
1%
#2770000
0%
#2775000
1%
#2780000
0%
#2785000
1%
#2790000
0%
#2795000
1%
#2800000
0%
#2805000
1%
#2810000
0%
#2815000
1%
#2820000
0%
#2825000
1%
#2830000
0%
#2835000
1*
1%
#2840000
0%
#2845000
b0 +
b1000 5
b1000 -
0*
b11100 )
b11100 ,
1%
#2850000
0%
#2855000
1%
#2860000
0%
#2865000
1%
#2870000
0%
#2875000
1%
#2880000
0%
#2885000
1%
#2890000
0%
#2895000
1%
#2900000
0%
#2905000
1%
#2910000
0%
#2915000
1%
#2920000
0%
#2925000
1%
#2930000
0%
#2935000
1*
1%
#2940000
0%
#2945000
b10000 +
b1001 5
b1001 -
0*
b11101 )
b11101 ,
1%
#2950000
0%
#2955000
1%
#2960000
0%
#2965000
1%
#2970000
0%
#2975000
1%
#2980000
0%
#2985000
1%
#2990000
0%
#2995000
1%
#3000000
0%
#3005000
1%
#3010000
0%
#3015000
1%
#3020000
0%
#3025000
1%
#3030000
0%
#3035000
1*
1%
#3040000
0%
#3045000
b1000000 +
b0 5
b0 -
b11 .
0*
b11110 )
b11110 ,
1%
#3050000
0%
#3055000
1%
#3060000
0%
#3065000
1%
#3070000
0%
#3075000
1%
#3080000
0%
#3085000
1%
